{
    "duik": [
        {
            "languageId": "zh_HANS",
            "languageName": "简体中文",
            "version": "1.0"
        },
        {
            "translations": [
                {
                    "comment": "",
                    "context": "",
                    "contextId": 0,
                    "source": "INSTALLATION",
                    "translation": "安装指南"
                },
                {
                    "comment": "",
                    "context": "",
                    "contextId": 0,
                    "source": "Please, check the box called 'Allow Scripts to write files...' in the general preferences of After Effects.",
                    "translation": "请在After Effects中的通用设置里勾选“允许脚本写入文件…”"
                },
                {
                    "comment": "",
                    "context": "",
                    "contextId": 0,
                    "source": "A new version of Duik is available,\\ngo to http://rainboxprod.coop to download it",
                    "translation": "已发现新版的Duik，\\n前往 http://rainboxprod.coop 下载"
                },
                {
                    "comment": "",
                    "context": "",
                    "contextId": 0,
                    "source": "UPDATE AVAILABLE -\\n\\nA new version of Duik is available!\\nVersion: ",
                    "translation": "已有升级可用 - \\n\\n新版Duik已可用！\\n版本号："
                },
                {
                    "comment": "",
                    "context": "",
                    "contextId": 0,
                    "source": "Launch Duik",
                    "translation": "启动Duik"
                },
                {
                    "comment": "",
                    "context": "",
                    "contextId": 0,
                    "source": "After Effects must be restarted\\n\\nto complete the installation of Duik\\n\\nMay the god(s?) of animation be with you!\\n\\n",
                    "translation": "After Effects需要重启\\n\\n来完成Duik的安装\\n\\n愿动画之神与你同在！"
                },
                {
                    "comment": "",
                    "context": "",
                    "contextId": 0,
                    "source": "Open the file 'presetEffects.xml':\\nRight click on\\nApplications/Adobe After Effects/Adobe After Effects.app,\\nSelect 'Show package contents', go to\\nContents/Resources/PresetEffects.xml.",
                    "translation": "打开“presetEffects.xml”文件：\\n右键单击\\nApplications/Adobe After Effects/Adobe After Effects.app，\\n选择“显示包内容”，进入\\nContents/Resources/PresetEffects.xml。"
                },
                {
                    "comment": "",
                    "context": "",
                    "contextId": 0,
                    "source": "Copy the content of the box below,\\nhit Cmd+A\\nto select all the text,\\nthen Cmd+C to copy it.",
                    "translation": "拷贝下面文本框内的内容，\\n按cmd+A\\n全选文本，\\n然后按cmd+C来拷贝它。"
                },
                {
                    "comment": "",
                    "context": "",
                    "contextId": 0,
                    "source": "Paste this text in the file 'presetEffects.xml'\\njust BEFORE the last line: '</effects>'.",
                    "translation": "在文件“presetEffects.xml”的最后一个“</effects>”的*上一行*\\n粘贴拷贝的内容"
                },
                {
                    "comment": "",
                    "context": "",
                    "contextId": 0,
                    "source": "Next",
                    "translation": "下一步"
                },
                {
                    "comment": "",
                    "context": "",
                    "contextId": 0,
                    "source": "ERROR",
                    "translation": "错误"
                },
                {
                    "comment": "",
                    "context": "",
                    "contextId": 0,
                    "source": "Duik - Loading icons",
                    "translation": "Duik - 载入图标"
                },
                {
                    "comment": "",
                    "context": "",
                    "contextId": 0,
                    "source": "Duik - Loading functions",
                    "translation": "Duik - 载入功能"
                },
                {
                    "comment": "",
                    "context": "",
                    "contextId": 0,
                    "source": "blade",
                    "translation": "肩胛骨"
                },
                {
                    "comment": "",
                    "context": "",
                    "contextId": 0,
                    "source": "shoulder",
                    "translation": "肩膀"
                },
                {
                    "comment": "",
                    "context": "",
                    "contextId": 0,
                    "source": "arm",
                    "translation": "上臂"
                },
                {
                    "comment": "",
                    "context": "",
                    "contextId": 0,
                    "source": "radius",
                    "translation": "桡骨"
                },
                {
                    "comment": "",
                    "context": "",
                    "contextId": 0,
                    "source": "elbow",
                    "translation": "肘"
                },
                {
                    "comment": "",
                    "context": "",
                    "contextId": 0,
                    "source": "palm",
                    "translation": "手掌"
                },
                {
                    "comment": "",
                    "context": "",
                    "contextId": 0,
                    "source": "claws",
                    "translation": "爪"
                },
                {
                    "comment": "",
                    "context": "",
                    "contextId": 0,
                    "source": "finger",
                    "translation": "指"
                },
                {
                    "comment": "",
                    "context": "",
                    "contextId": 0,
                    "source": "tiptoe",
                    "translation": "脚尖"
                },
                {
                    "comment": "",
                    "context": "",
                    "contextId": 0,
                    "source": "back",
                    "translation": "手脚背"
                },
                {
                    "comment": "",
                    "context": "",
                    "contextId": 0,
                    "source": "femur",
                    "translation": "股骨"
                },
                {
                    "comment": "",
                    "context": "",
                    "contextId": 0,
                    "source": "tibia",
                    "translation": "胫骨"
                },
                {
                    "comment": "",
                    "context": "",
                    "contextId": 0,
                    "source": "calf",
                    "translation": "腓"
                },
                {
                    "comment": "",
                    "context": "",
                    "contextId": 0,
                    "source": "None",
                    "translation": "无"
                },
                {
                    "comment": "",
                    "context": "",
                    "contextId": 0,
                    "source": "Carpus",
                    "translation": "腕"
                },
                {
                    "comment": "",
                    "context": "",
                    "contextId": 0,
                    "source": "Radius",
                    "translation": "桡骨"
                },
                {
                    "comment": "",
                    "context": "",
                    "contextId": 0,
                    "source": "The autorig does not work with 3D Layers",
                    "translation": "自动绑定对3D图层不起效"
                },
                {
                    "comment": "",
                    "context": "",
                    "contextId": 0,
                    "source": "R_",
                    "translation": "右_"
                },
                {
                    "comment": "",
                    "context": "",
                    "contextId": 0,
                    "source": "L_",
                    "translation": "左_"
                },
                {
                    "comment": "",
                    "context": "",
                    "contextId": 0,
                    "source": "tarsus",
                    "translation": "踝"
                },
                {
                    "comment": "",
                    "context": "",
                    "contextId": 0,
                    "source": "toes",
                    "translation": "趾"
                },
                {
                    "comment": "",
                    "context": "",
                    "contextId": 0,
                    "source": "Femur",
                    "translation": "股骨"
                },
                {
                    "comment": "",
                    "context": "",
                    "contextId": 0,
                    "source": "Right leg",
                    "translation": "右腿"
                },
                {
                    "comment": "",
                    "context": "",
                    "contextId": 0,
                    "source": "Duik - Back Leg Autorig",
                    "translation": "Duik - 背腿自动绑定"
                },
                {
                    "comment": "",
                    "context": "",
                    "contextId": 0,
                    "source": "hips",
                    "translation": "髋"
                },
                {
                    "comment": "",
                    "context": "",
                    "contextId": 0,
                    "source": "abdomen",
                    "translation": "腹"
                },
                {
                    "comment": "",
                    "context": "",
                    "contextId": 0,
                    "source": "torso",
                    "translation": "躯干"
                },
                {
                    "comment": "",
                    "context": "",
                    "contextId": 0,
                    "source": "thorax",
                    "translation": "胸甲"
                },
                {
                    "comment": "",
                    "context": "",
                    "contextId": 0,
                    "source": "Head",
                    "translation": "头"
                },
                {
                    "comment": "",
                    "context": "",
                    "contextId": 0,
                    "source": "Duik - Spine Autorig",
                    "translation": "Duik - 脊柱自动绑定"
                },
                {
                    "comment": "",
                    "context": "",
                    "contextId": 0,
                    "source": "Hips",
                    "translation": "髋"
                },
                {
                    "comment": "",
                    "context": "",
                    "contextId": 0,
                    "source": "Duik - Tail Autorig",
                    "translation": "Duik - 尾部自动绑定"
                },
                {
                    "comment": "",
                    "context": "",
                    "contextId": 0,
                    "source": "Select the bones and the controller before creating IK",
                    "translation": "选择骨节和控制器来创建IK"
                },
                {
                    "comment": "",
                    "context": "",
                    "contextId": 0,
                    "source": "Duik - IK",
                    "translation": "Duik - IK"
                },
                {
                    "comment": "",
                    "context": "",
                    "contextId": 0,
                    "source": "Duik - IK Goal",
                    "translation": "Duik - IK目标约束"
                },
                {
                    "comment": "",
                    "context": "",
                    "contextId": 0,
                    "source": "Attention",
                    "translation": "注意"
                },
                {
                    "comment": "",
                    "context": "",
                    "contextId": 0,
                    "source": "Controllers",
                    "translation": "控制器"
                },
                {
                    "comment": "",
                    "context": "",
                    "contextId": 0,
                    "source": "Duik - Lock Controllers",
                    "translation": "Duik - 锁定控制器"
                },
                {
                    "comment": "",
                    "context": "",
                    "contextId": 0,
                    "source": "Duik - Unhide Controllers",
                    "translation": "Duik - 显示隐藏的控制器"
                },
                {
                    "comment": "",
                    "context": "",
                    "contextId": 0,
                    "source": "Duik - Bone",
                    "translation": "Duik - 骨骼"
                },
                {
                    "comment": "",
                    "context": "",
                    "contextId": 0,
                    "source": "The layers are at the same place.",
                    "translation": "图层在相同的位置"
                },
                {
                    "comment": "",
                    "context": "",
                    "contextId": 0,
                    "source": " pixels",
                    "translation": " 像素"
                },
                {
                    "comment": "",
                    "context": "",
                    "contextId": 0,
                    "source": "Select a layer to apply Zero",
                    "translation": "选择一个图层以运用归零"
                },
                {
                    "comment": "",
                    "context": "",
                    "contextId": 0,
                    "source": "Duik - Rotation Morph",
                    "translation": "旋转驱动帧"
                },
                {
                    "comment": "",
                    "context": "",
                    "contextId": 0,
                    "source": "Duik - Search and replace",
                    "translation": "Duik - 搜索和替换"
                },
                {
                    "comment": "",
                    "context": "",
                    "contextId": 0,
                    "source": "Duik - List",
                    "translation": "Duik - 列表"
                },
                {
                    "comment": "",
                    "context": "",
                    "contextId": 0,
                    "source": "Import rig: ",
                    "translation": "导入绑定："
                },
                {
                    "comment": "",
                    "context": "",
                    "contextId": 0,
                    "source": "Select the property where to apply the \\\"wiggle\\\" function",
                    "translation": "选择需要执行“抖动”的属性"
                },
                {
                    "comment": "",
                    "context": "",
                    "contextId": 0,
                    "source": "Invalid Radius",
                    "translation": "无效的半径"
                },
                {
                    "comment": "",
                    "context": "",
                    "contextId": 0,
                    "source": "Lens Controller",
                    "translation": "控制器"
                },
                {
                    "comment": "",
                    "context": "",
                    "contextId": 0,
                    "source": "Distance Link",
                    "translation": "位移驱动帧"
                },
                {
                    "comment": "",
                    "context": "",
                    "contextId": 0,
                    "source": "Cannot create expression on this effect",
                    "translation": "无法在此效果上创建表达式"
                },
                {
                    "comment": "",
                    "context": "",
                    "contextId": 0,
                    "source": "Select the effect where you want to create the spring",
                    "translation": "选择一个效果以创建回弹"
                },
                {
                    "comment": "",
                    "context": "",
                    "contextId": 0,
                    "source": "No layer selected",
                    "translation": "没有图层被选中"
                },
                {
                    "comment": "",
                    "context": "",
                    "contextId": 0,
                    "source": "Duik Auto-Exposure",
                    "translation": "Duik 自动曝光表"
                },
                {
                    "comment": "",
                    "context": "",
                    "contextId": 0,
                    "source": "Duik - Paint Rigging",
                    "translation": "Duik - 笔触绑定"
                },
                {
                    "comment": "",
                    "context": "",
                    "contextId": 0,
                    "source": "Duik - Blink",
                    "translation": "Duik - 闪动"
                },
                {
                    "comment": "",
                    "context": "",
                    "contextId": 0,
                    "source": "Duik - Move away",
                    "translation": "Duik - 沿方向移动"
                },
                {
                    "comment": "",
                    "context": "",
                    "contextId": 0,
                    "source": "Duik - New celluloid",
                    "translation": "Duik - 新赛璐珞"
                },
                {
                    "comment": "",
                    "context": "",
                    "contextId": 0,
                    "source": "Please select the layers from which you want to save animation",
                    "translation": "请选择需要保存动画的图层"
                },
                {
                    "comment": "",
                    "context": "",
                    "contextId": 0,
                    "source": "Pasted animation on ",
                    "translation": "将动画粘贴在"
                },
                {
                    "comment": "",
                    "context": "",
                    "contextId": 0,
                    "source": "Create a morpher",
                    "translation": "创建驱动帧"
                },
                {
                    "comment": "",
                    "context": "",
                    "contextId": 0,
                    "source": "No camera selected",
                    "translation": "没有摄像机被选择"
                },
                {
                    "comment": "",
                    "context": "",
                    "contextId": 0,
                    "source": "Camera Controller",
                    "translation": "摄像机控制器"
                },
                {
                    "comment": "",
                    "context": "",
                    "contextId": 0,
                    "source": " position",
                    "translation": "位移"
                },
                {
                    "comment": "",
                    "context": "",
                    "contextId": 0,
                    "source": "Duik - Multiplane",
                    "translation": "Duik - 多平面"
                },
                {
                    "comment": "",
                    "context": "",
                    "contextId": 0,
                    "source": "Duik - Import TVPaint Camera",
                    "translation": "Duik - 导入 TVPaint 摄像机"
                },
                {
                    "comment": "",
                    "context": "",
                    "contextId": 0,
                    "source": "Duik - Interpolation",
                    "translation": "Duik - 补间"
                },
                {
                    "comment": "",
                    "context": "",
                    "contextId": 0,
                    "source": "Cancel",
                    "translation": "取消"
                },
                {
                    "comment": "",
                    "context": "",
                    "contextId": 0,
                    "source": "Close",
                    "translation": "关闭"
                },
                {
                    "comment": "",
                    "context": "",
                    "contextId": 0,
                    "source": "Notes",
                    "translation": "记事本"
                },
                {
                    "comment": "",
                    "context": "",
                    "contextId": 0,
                    "source": "Simple notepad, with auto-save.",
                    "translation": "带有自动保存的简单的记事本。"
                },
                {
                    "comment": "",
                    "context": "",
                    "contextId": 0,
                    "source": "Automation",
                    "translation": "自动动画"
                },
                {
                    "comment": "",
                    "context": "",
                    "contextId": 0,
                    "source": "Cameras",
                    "translation": "摄像机"
                },
                {
                    "comment": "",
                    "context": "",
                    "contextId": 0,
                    "source": "Help!",
                    "translation": "帮助！"
                },
                {
                    "comment": "",
                    "context": "",
                    "contextId": 0,
                    "source": "Tool boxes",
                    "translation": "工具箱"
                },
                {
                    "comment": "",
                    "context": "",
                    "contextId": 0,
                    "source": "Warning, this is a version for testing purposes only!",
                    "translation": "警告，这个版本仅做测试用！"
                },
                {
                    "comment": "",
                    "context": "",
                    "contextId": 0,
                    "source": "A form is available at http://duiktest.duduf.net",
                    "translation": "在 https://duiktest.duduf.net 上有一个列表"
                },
                {
                    "comment": "",
                    "context": "",
                    "contextId": 0,
                    "source": "If you need help using Duik,",
                    "translation": "如果你在使用Duik时需要帮助，"
                },
                {
                    "comment": "",
                    "context": "",
                    "contextId": 0,
                    "source": "Duduf Training, documents and tutorials:",
                    "translation": "Duduf的培训，文档和教程："
                },
                {
                    "comment": "",
                    "context": "",
                    "contextId": 0,
                    "source": "License: Duik is free software,",
                    "translation": "许可：Duik是一个自由软件，"
                },
                {
                    "comment": "",
                    "context": "",
                    "contextId": 0,
                    "source": "Credits:",
                    "translation": "职员表："
                },
                {
                    "comment": "",
                    "context": "",
                    "contextId": 0,
                    "source": "Kevin Schires - Including images in the script",
                    "translation": "Kevin Schires - 将UI图片转换为文本格式"
                },
                {
                    "comment": "",
                    "context": "",
                    "contextId": 0,
                    "source": "Zeg - UI designer",
                    "translation": "Zeg - 用户界面设计"
                },
                {
                    "comment": "",
                    "context": "",
                    "contextId": 0,
                    "source": "UI",
                    "translation": "用户界面"
                },
                {
                    "comment": "",
                    "context": "",
                    "contextId": 0,
                    "source": "Default",
                    "translation": "默认"
                },
                {
                    "comment": "",
                    "context": "",
                    "contextId": 0,
                    "source": "Use dropdown",
                    "translation": "使用下拉菜单"
                },
                {
                    "comment": "",
                    "context": "",
                    "contextId": 0,
                    "source": "Expert Mode",
                    "translation": "专家模式"
                },
                {
                    "comment": "",
                    "context": "",
                    "contextId": 0,
                    "source": "Check for update at startup",
                    "translation": "启动时自动检查更新"
                },
                {
                    "comment": "",
                    "context": "",
                    "contextId": 0,
                    "source": "Duik is up-to-date",
                    "translation": "Duik是最新的"
                },
                {
                    "comment": "",
                    "context": "",
                    "contextId": 0,
                    "source": "Type :",
                    "translation": "样式："
                },
                {
                    "comment": "",
                    "context": "",
                    "contextId": 0,
                    "source": "Null",
                    "translation": "空物体"
                },
                {
                    "comment": "",
                    "context": "",
                    "contextId": 0,
                    "source": "Auto size",
                    "translation": "自动尺寸"
                },
                {
                    "comment": "",
                    "context": "",
                    "contextId": 0,
                    "source": "Medium",
                    "translation": "中"
                },
                {
                    "comment": "",
                    "context": "",
                    "contextId": 0,
                    "source": "Color:",
                    "translation": "颜色："
                },
                {
                    "comment": "",
                    "context": "",
                    "contextId": 0,
                    "source": "Top",
                    "translation": "顶层"
                },
                {
                    "comment": "",
                    "context": "",
                    "contextId": 0,
                    "source": "Over layer",
                    "translation": "在该层之上"
                },
                {
                    "comment": "",
                    "context": "",
                    "contextId": 0,
                    "source": "Type",
                    "translation": "样式"
                },
                {
                    "comment": "",
                    "context": "",
                    "contextId": 0,
                    "source": "Interpolations",
                    "translation": "补间"
                },
                {
                    "comment": "",
                    "context": "",
                    "contextId": 0,
                    "source": "Warning, interactive update can create a LOT of history items (Undos) and could easily fill up your entire history.",
                    "translation": "警告，交互式更新会产生大量的历史记录（Undos），这很容易填满你的整个返回操作列表"
                },
                {
                    "comment": "",
                    "context": "",
                    "contextId": 0,
                    "source": "Copy/paste",
                    "translation": "复制/粘贴"
                },
                {
                    "comment": "",
                    "context": "",
                    "contextId": 0,
                    "source": "Use layer indexes",
                    "translation": "使用图层索引"
                },
                {
                    "comment": "",
                    "context": "",
                    "contextId": 0,
                    "source": "Auto-Rig",
                    "translation": "自动绑定"
                },
                {
                    "comment": "",
                    "context": "",
                    "contextId": 0,
                    "source": "IK",
                    "translation": "IK"
                },
                {
                    "comment": "",
                    "context": "",
                    "contextId": 0,
                    "source": "Orient to path",
                    "translation": "沿路径自动旋转"
                },
                {
                    "comment": "",
                    "context": "",
                    "contextId": 0,
                    "source": "Bezier IK",
                    "translation": "贝塞尔 IK"
                },
                {
                    "comment": "",
                    "context": "",
                    "contextId": 0,
                    "source": "Rot Morph",
                    "translation": "旋转驱动帧"
                },
                {
                    "comment": "",
                    "context": "",
                    "contextId": 0,
                    "source": "Controller",
                    "translation": "控制器"
                },
                {
                    "comment": "",
                    "context": "",
                    "contextId": 0,
                    "source": "Zero",
                    "translation": "归零"
                },
                {
                    "comment": "",
                    "context": "",
                    "contextId": 0,
                    "source": "List",
                    "translation": "列表"
                },
                {
                    "comment": "",
                    "context": "",
                    "contextId": 0,
                    "source": "Rename",
                    "translation": "重命名"
                },
                {
                    "comment": "",
                    "context": "",
                    "contextId": 0,
                    "source": "Measure",
                    "translation": "测量"
                },
                {
                    "comment": "",
                    "context": "",
                    "contextId": 0,
                    "source": "Replace",
                    "translation": "替换"
                },
                {
                    "comment": "",
                    "context": "",
                    "contextId": 0,
                    "source": "Lock property",
                    "translation": "锁定属性"
                },
                {
                    "comment": "",
                    "context": "",
                    "contextId": 0,
                    "source": "Roving",
                    "translation": "流动关键帧"
                },
                {
                    "comment": "",
                    "context": "",
                    "contextId": 0,
                    "source": "Ease In",
                    "translation": "缓入"
                },
                {
                    "comment": "",
                    "context": "",
                    "contextId": 0,
                    "source": "Easy Ease",
                    "translation": "缓动"
                },
                {
                    "comment": "",
                    "context": "",
                    "contextId": 0,
                    "source": "Hold",
                    "translation": "静止"
                },
                {
                    "comment": "",
                    "context": "",
                    "contextId": 0,
                    "source": "Speed",
                    "translation": "速度"
                },
                {
                    "comment": "",
                    "context": "",
                    "contextId": 0,
                    "source": "Ease In influence",
                    "translation": "缓入强度"
                },
                {
                    "comment": "",
                    "context": "",
                    "contextId": 0,
                    "source": "Ease Out influence",
                    "translation": "缓出强度"
                },
                {
                    "comment": "",
                    "context": "",
                    "contextId": 0,
                    "source": "Get",
                    "translation": "提取"
                },
                {
                    "comment": "",
                    "context": "",
                    "contextId": 0,
                    "source": "Spatial interpolation",
                    "translation": "空间插值"
                },
                {
                    "comment": "",
                    "context": "",
                    "contextId": 0,
                    "source": "Bezier",
                    "translation": "贝塞尔"
                },
                {
                    "comment": "",
                    "context": "",
                    "contextId": 0,
                    "source": "Morpher",
                    "translation": "驱动帧"
                },
                {
                    "comment": "",
                    "context": "",
                    "contextId": 0,
                    "source": "Keyframes",
                    "translation": "关键帧"
                },
                {
                    "comment": "",
                    "context": "",
                    "contextId": 0,
                    "source": "Copy animation from selected layers",
                    "translation": "从选择的层复制动画"
                },
                {
                    "comment": "",
                    "context": "",
                    "contextId": 0,
                    "source": "Automatically paste animation in the comp (using layer names)",
                    "translation": "（以图层名称的方式）在合成中（以图层名称的方式），自动粘贴动画"
                },
                {
                    "comment": "",
                    "context": "",
                    "contextId": 0,
                    "source": "Cel animation tools",
                    "translation": "赛璐珞动画工具"
                },
                {
                    "comment": "",
                    "context": "",
                    "contextId": 0,
                    "source": "Import rig in comp",
                    "translation": "将绑定导入合成"
                },
                {
                    "comment": "",
                    "context": "",
                    "contextId": 0,
                    "source": "Wiggle",
                    "translation": "抖动"
                },
                {
                    "comment": "",
                    "context": "",
                    "contextId": 0,
                    "source": "Swing",
                    "translation": "摇晃"
                },
                {
                    "comment": "",
                    "context": "",
                    "contextId": 0,
                    "source": "The property will automatically bounce like a spring",
                    "translation": "属性值会像弹簧一样回弹"
                },
                {
                    "comment": "",
                    "context": "",
                    "contextId": 0,
                    "source": "Makes the property blink.",
                    "translation": "让属性闪动"
                },
                {
                    "comment": "",
                    "context": "",
                    "contextId": 0,
                    "source": "Automates the rotation of a wheel while moving the layer",
                    "translation": "自动旋转轮子来贴合图层的位移"
                },
                {
                    "comment": "",
                    "context": "",
                    "contextId": 0,
                    "source": "Creates a lens flare with selected layers",
                    "translation": "用选定的多个图层创建镜头光晕"
                },
                {
                    "comment": "",
                    "context": "",
                    "contextId": 0,
                    "source": "A simple controller to move away a layer from its parent",
                    "translation": "将子物体沿着与父级相同的方位移动"
                },
                {
                    "comment": "",
                    "context": "",
                    "contextId": 0,
                    "source": "Links an effect with the distance with another layer",
                    "translation": "用另一个图层的位移来控制一个效果"
                },
                {
                    "comment": "",
                    "context": "",
                    "contextId": 0,
                    "source": "Changes the exposure of the animation on the selected property",
                    "translation": "修改选定属性的动画曝光表"
                },
                {
                    "comment": "",
                    "context": "",
                    "contextId": 0,
                    "source": "Rig the paint effects to be able to animate all strokes as if there was only one.",
                    "translation": "将所有的笔触效果绑定为同一个动画方便K动画。"
                },
                {
                    "comment": "",
                    "context": "",
                    "contextId": 0,
                    "source": "Rig the paint effects to be able to animate selected strokes as if there was only one.",
                    "translation": "将选定的笔触效果绑定为同一个动画方便K动画。"
                },
                {
                    "comment": "",
                    "context": "",
                    "contextId": 0,
                    "source": "Randomize properties and layers.",
                    "translation": "随机属性值和图层"
                },
                {
                    "comment": "",
                    "context": "",
                    "contextId": 0,
                    "source": "Time remapping tools.",
                    "translation": "时间重映射工具。"
                },
                {
                    "comment": "",
                    "context": "",
                    "contextId": 0,
                    "source": "Creates animation controllers for a camera",
                    "translation": "为摄像机创建动画控制器"
                },
                {
                    "comment": "",
                    "context": "",
                    "contextId": 0,
                    "source": "Links the distance of the layer from the camera to its scale, so its apparent size won't change.",
                    "translation": "将图层到摄像机的距离与图层的缩放链接起来，以保证图层比例不会改变"
                },
                {
                    "comment": "",
                    "context": "",
                    "contextId": 0,
                    "source": "Creates multiplane controllers to use as a 2D camera",
                    "translation": "创建多平面控制器以便用2D摄像机来模拟空间"
                },
                {
                    "comment": "",
                    "context": "",
                    "contextId": 0,
                    "source": "Imports a camera from TVPaint.",
                    "translation": "从 TVPaint 中导入相机"
                },
                {
                    "comment": "",
                    "context": "",
                    "contextId": 0,
                    "source": "X position",
                    "translation": "X 坐标"
                },
                {
                    "comment": "",
                    "context": "",
                    "contextId": 0,
                    "source": "Scale",
                    "translation": "缩放"
                },
                {
                    "comment": "",
                    "context": "",
                    "contextId": 0,
                    "source": "Custom",
                    "translation": "自定义"
                },
                {
                    "comment": "",
                    "context": "",
                    "contextId": 0,
                    "source": "Custom size",
                    "translation": "自定义尺寸"
                },
                {
                    "comment": "",
                    "context": "",
                    "contextId": 0,
                    "source": "Red",
                    "translation": "红色"
                },
                {
                    "comment": "",
                    "context": "",
                    "contextId": 0,
                    "source": "Blue",
                    "translation": "蓝色"
                },
                {
                    "comment": "",
                    "context": "",
                    "contextId": 0,
                    "source": "Magenta",
                    "translation": "品红色"
                },
                {
                    "comment": "",
                    "context": "",
                    "contextId": 0,
                    "source": "White",
                    "translation": "白色"
                },
                {
                    "comment": "",
                    "context": "",
                    "contextId": 0,
                    "source": "Dark Gray",
                    "translation": "暗灰色"
                },
                {
                    "comment": "",
                    "context": "",
                    "contextId": 0,
                    "source": "Custom color",
                    "translation": "自定义颜色"
                },
                {
                    "comment": "",
                    "context": "",
                    "contextId": 0,
                    "source": "Warning! When controllers are locked,\\nthey should be unlocked before parenting.",
                    "translation": "警告！当控制器被锁定时，\\n它们在创建父子关系时必须先解锁"
                },
                {
                    "comment": "",
                    "context": "",
                    "contextId": 0,
                    "source": "Lock selected controllers\\n(all controllers if none selected)",
                    "translation": "锁定所选控制器\\n（若没有选择则锁定所有控制器）"
                },
                {
                    "comment": "",
                    "context": "",
                    "contextId": 0,
                    "source": "Hide selected controllers\\n(all controllers if none selected)",
                    "translation": "隐藏所选控制器\\n（若没有选择则隐藏所有控制器）"
                },
                {
                    "comment": "",
                    "context": "",
                    "contextId": 0,
                    "source": "Back",
                    "translation": "退后"
                },
                {
                    "comment": "",
                    "context": "",
                    "contextId": 0,
                    "source": "Create",
                    "translation": "创建"
                },
                {
                    "comment": "",
                    "context": "",
                    "contextId": 0,
                    "source": "3-Layer IK",
                    "translation": "三图层IK"
                },
                {
                    "comment": "",
                    "context": "",
                    "contextId": 0,
                    "source": "1-Layer IK & Goal",
                    "translation": "单图层IK&目标约束"
                },
                {
                    "comment": "",
                    "context": "",
                    "contextId": 0,
                    "source": "1-Layer IK (LookAt)",
                    "translation": "一图层IK（LookAt）"
                },
                {
                    "comment": "",
                    "context": "",
                    "contextId": 0,
                    "source": "Left/Right view",
                    "translation": "左/右视图"
                },
                {
                    "comment": "",
                    "context": "",
                    "contextId": 0,
                    "source": "Simple",
                    "translation": "简单曲线"
                },
                {
                    "comment": "",
                    "context": "",
                    "contextId": 0,
                    "source": "Cubic",
                    "translation": "三次方曲线"
                },
                {
                    "comment": "",
                    "context": "",
                    "contextId": 0,
                    "source": "Pins",
                    "translation": "图钉"
                },
                {
                    "comment": "",
                    "context": "",
                    "contextId": 0,
                    "source": "Name",
                    "translation": "名称"
                },
                {
                    "comment": "",
                    "context": "",
                    "contextId": 0,
                    "source": "Suffix",
                    "translation": "后缀"
                },
                {
                    "comment": "",
                    "context": "",
                    "contextId": 0,
                    "source": "digits.",
                    "translation": "位字符"
                },
                {
                    "comment": "",
                    "context": "",
                    "contextId": 0,
                    "source": "Number from",
                    "translation": "首位编号"
                },
                {
                    "comment": "",
                    "context": "",
                    "contextId": 0,
                    "source": "Current comp",
                    "translation": "当前合成"
                },
                {
                    "comment": "",
                    "context": "",
                    "contextId": 0,
                    "source": "Expressions",
                    "translation": "表达式"
                },
                {
                    "comment": "",
                    "context": "",
                    "contextId": 0,
                    "source": "Comps",
                    "translation": "合成"
                },
                {
                    "comment": "",
                    "context": "",
                    "contextId": 0,
                    "source": "Folders",
                    "translation": "目录"
                },
                {
                    "comment": "",
                    "context": "",
                    "contextId": 0,
                    "source": "All Items",
                    "translation": "所有项目"
                },
                {
                    "comment": "",
                    "context": "",
                    "contextId": 0,
                    "source": "Active comp",
                    "translation": "活动的合成"
                },
                {
                    "comment": "",
                    "context": "",
                    "contextId": 0,
                    "source": "Selected",
                    "translation": "选中的"
                },
                {
                    "comment": "",
                    "context": "",
                    "contextId": 0,
                    "source": "All layers",
                    "translation": "所有图层"
                },
                {
                    "comment": "",
                    "context": "",
                    "contextId": 0,
                    "source": "Case sensitive",
                    "translation": "区分大小写"
                },
                {
                    "comment": "",
                    "context": "",
                    "contextId": 0,
                    "source": "Loop out",
                    "translation": "出点循环"
                },
                {
                    "comment": "",
                    "context": "",
                    "contextId": 0,
                    "source": "Loop in",
                    "translation": "入点循环"
                },
                {
                    "comment": "",
                    "context": "",
                    "contextId": 0,
                    "source": "Time Remap",
                    "translation": "时间重映射"
                },
                {
                    "comment": "",
                    "context": "",
                    "contextId": 0,
                    "source": "Fixed",
                    "translation": "固定间距"
                },
                {
                    "comment": "",
                    "context": "",
                    "contextId": 0,
                    "source": "Lower exp. limit: ",
                    "translation": "最小曝光长度限制："
                },
                {
                    "comment": "",
                    "context": "",
                    "contextId": 0,
                    "source": "Precision: ",
                    "translation": "精确度："
                },
                {
                    "comment": "",
                    "context": "",
                    "contextId": 0,
                    "source": "Sync",
                    "translation": "同步"
                },
                {
                    "comment": "",
                    "context": "",
                    "contextId": 0,
                    "source": "All",
                    "translation": "全部"
                },
                {
                    "comment": "",
                    "context": "",
                    "contextId": 0,
                    "source": "Layer:",
                    "translation": "图层："
                },
                {
                    "comment": "",
                    "context": "",
                    "contextId": 0,
                    "source": "Lower accuracy can speed up analysis",
                    "translation": "更低的准确度将提升分析速度"
                },
                {
                    "comment": "",
                    "context": "",
                    "contextId": 0,
                    "source": "Higher tolerance will result in higher exposure",
                    "translation": "更大的容差度将得到更长的曝光时间"
                },
                {
                    "comment": "",
                    "context": "",
                    "contextId": 0,
                    "source": "G",
                    "translation": "G"
                },
                {
                    "comment": "",
                    "context": "",
                    "contextId": 0,
                    "source": "A",
                    "translation": "A"
                },
                {
                    "comment": "",
                    "context": "",
                    "contextId": 0,
                    "source": "Analyze layer to detect exposure",
                    "translation": "分析图层以得到曝光时间"
                },
                {
                    "comment": "",
                    "context": "",
                    "contextId": 0,
                    "source": "Single Layer",
                    "translation": "单一图层"
                },
                {
                    "comment": "",
                    "context": "",
                    "contextId": 0,
                    "source": "New Cel.",
                    "translation": "新赛璐珞"
                },
                {
                    "comment": "",
                    "context": "",
                    "contextId": 0,
                    "source": "Onion skin",
                    "translation": "洋葱皮"
                },
                {
                    "comment": "",
                    "context": "",
                    "contextId": 0,
                    "source": "Onion skin duration (frames)",
                    "translation": "洋葱皮持续时间（帧）"
                },
                {
                    "comment": "",
                    "context": "",
                    "contextId": 0,
                    "source": "Out Opacity",
                    "translation": "出点不透明度"
                },
                {
                    "comment": "",
                    "context": "",
                    "contextId": 0,
                    "source": "Apply Onion Skin",
                    "translation": "运动当前洋葱皮"
                },
                {
                    "comment": "",
                    "context": "",
                    "contextId": 0,
                    "source": "Next frame",
                    "translation": "后一帧"
                },
                {
                    "comment": "",
                    "context": "",
                    "contextId": 0,
                    "source": "All Dimensions",
                    "translation": "所有维度"
                },
                {
                    "comment": "",
                    "context": "",
                    "contextId": 0,
                    "source": "Name of this instance:",
                    "translation": "该实例的名称："
                },
                {
                    "comment": "",
                    "context": "",
                    "contextId": 0,
                    "source": "Import",
                    "translation": "导入"
                },
                {
                    "comment": "",
                    "context": "",
                    "contextId": 0,
                    "source": "Selected properties",
                    "translation": "所选的属性"
                },
                {
                    "comment": "",
                    "context": "",
                    "contextId": 0,
                    "source": "In points",
                    "translation": "入点"
                },
                {
                    "comment": "",
                    "context": "",
                    "contextId": 0,
                    "source": "Selected keyframes",
                    "translation": "所选的关键帧"
                },
                {
                    "comment": "",
                    "context": "",
                    "contextId": 0,
                    "source": "Values",
                    "translation": "数值"
                },
                {
                    "comment": "",
                    "context": "",
                    "contextId": 0,
                    "source": "Min",
                    "translation": "最小"
                },
                {
                    "comment": "",
                    "context": "",
                    "contextId": 0,
                    "source": "Layers:",
                    "translation": "图层"
                },
                {
                    "comment": "",
                    "context": "",
                    "contextId": 0,
                    "source": "Creates a 2D multiplane camera rig",
                    "translation": "创建3D多平面摄像机绑定"
                },
                {
                    "comment": "",
                    "context": "",
                    "contextId": 0,
                    "source": "Radius of the wheel, pixels",
                    "translation": "轮子的半径，单位，像素"
                },
                {
                    "comment": "",
                    "context": "",
                    "contextId": 0,
                    "source": "Measure with another object",
                    "translation": "测量到另一个物体间的距离"
                },
                {
                    "comment": "",
                    "context": "",
                    "contextId": 0,
                    "source": "Curved",
                    "translation": "沿曲线运动"
                },
                {
                    "comment": "",
                    "context": "",
                    "contextId": 0,
                    "source": "When the Spring is used on the position property of a layer,",
                    "translation": "当回弹用在一个图层的位移属性上时，"
                },
                {
                    "comment": "",
                    "context": "",
                    "contextId": 0,
                    "source": "Without simulation - Light",
                    "translation": "不进行解算 - 计算量小"
                },
                {
                    "comment": "",
                    "context": "",
                    "contextId": 0,
                    "source": "Simulated - Heavy computing",
                    "translation": "进行解算 - 大量计算"
                },
                {
                    "comment": "",
                    "context": "",
                    "contextId": 0,
                    "source": "Resulting animation may be smoother too.",
                    "translation": "最终动画也会更顺滑。"
                },
                {
                    "comment": "",
                    "context": "",
                    "contextId": 0,
                    "source": "Use a Null Object",
                    "translation": "使用空物体"
                },
                {
                    "comment": "",
                    "context": "",
                    "contextId": 0,
                    "source": "Use selected layer",
                    "translation": "使用选中图层"
                },
                {
                    "comment": "",
                    "context": "",
                    "contextId": 0,
                    "source": "Animate position",
                    "translation": "对位移K动画"
                },
                {
                    "comment": "",
                    "context": "",
                    "contextId": 0,
                    "source": "Import TVP Cam",
                    "translation": "导入 TVP 摄像机"
                },
                {
                    "comment": "",
                    "context": "",
                    "contextId": 0,
                    "source": "Ungulate",
                    "translation": "蹄行生物"
                },
                {
                    "comment": "",
                    "context": "",
                    "contextId": 0,
                    "source": "Digitigrade",
                    "translation": "趾行生物"
                },
                {
                    "comment": "",
                    "context": "",
                    "contextId": 0,
                    "source": "Plantigrade",
                    "translation": "掌行生物"
                },
                {
                    "comment": "",
                    "context": "",
                    "contextId": 0,
                    "source": "Full character",
                    "translation": "全身角色"
                },
                {
                    "comment": "",
                    "context": "",
                    "contextId": 0,
                    "source": "Back leg",
                    "translation": "后腿"
                },
                {
                    "comment": "",
                    "context": "",
                    "contextId": 0,
                    "source": "Tail",
                    "translation": "尾部"
                },
                {
                    "comment": "",
                    "context": "",
                    "contextId": 0,
                    "source": "Right Leg",
                    "translation": "右腿"
                },
                {
                    "comment": "",
                    "context": "",
                    "contextId": 0,
                    "source": "Shoulder blade, clavicle",
                    "translation": "肩胛骨，锁骨"
                },
                {
                    "comment": "",
                    "context": "",
                    "contextId": 0,
                    "source": "Ulna, radius, forearm, elbow",
                    "translation": "尺骨，桡骨，前臂，肘"
                },
                {
                    "comment": "",
                    "context": "",
                    "contextId": 0,
                    "source": "Claws, hoof, fingers",
                    "translation": "爪，蹄，指"
                },
                {
                    "comment": "",
                    "context": "",
                    "contextId": 0,
                    "source": "Tip, tiptoe",
                    "translation": "指尖，脚尖"
                },
                {
                    "comment": "",
                    "context": "",
                    "contextId": 0,
                    "source": "Remove All",
                    "translation": "清空所有"
                },
                {
                    "comment": "",
                    "context": "",
                    "contextId": 0,
                    "source": "Femur, thigh",
                    "translation": "股骨，大腿"
                },
                {
                    "comment": "",
                    "context": "",
                    "contextId": 0,
                    "source": "Tarsus, foot",
                    "translation": "脚踝，足部"
                },
                {
                    "comment": "",
                    "context": "",
                    "contextId": 0,
                    "source": "Spine Autorig",
                    "translation": "脊柱自动绑定"
                },
                {
                    "comment": "",
                    "context": "",
                    "contextId": 0,
                    "source": "From",
                    "translation": "从"
                },
                {
                    "comment": "",
                    "context": "",
                    "contextId": 0,
                    "source": "Spine, torso, chest, thorax",
                    "translation": "脊柱，躯干，胸腔，胸甲"
                },
                {
                    "comment": "",
                    "context": "",
                    "contextId": 0,
                    "source": "Tail Autorig",
                    "translation": "尾部自动绑定"
                },
                {
                    "comment": "",
                    "context": "",
                    "contextId": 0,
                    "source": "Two curves",
                    "translation": "两条曲线"
                },
                {
                    "comment": "",
                    "context": "",
                    "contextId": 0,
                    "source": "Duik must be restarted to apply changes.",
                    "translation": "必须重启Duik以使更改起效"
                },
                {
                    "comment": "",
                    "context": "",
                    "contextId": 0,
                    "source": "Please be patient while Duik is doing its magic.",
                    "translation": "请耐心等待Duik完成它的魔法"
                }
            ]
        }
    ]
}
